kcore_migrate/__init__.py
kcore_migrate/base.py
kcore_migrate/dependency_resolver.py
kcore_migrate/ibackend.py
kcore_migrate/imigrator.py
kcore_migrate/migrator.py
kcore_migrate/utils.py
kcore_migrate/backends/__init__.py
kcore_migrate/backends/asyncpg.py
kcore_migrate-0.0.3.dist-info/LICENCE
kcore_migrate-0.0.3.dist-info/METADATA
kcore_migrate-0.0.3.dist-info/WHEEL
kcore_migrate-0.0.3.dist-info/top_level.txt
kcore_migrate-0.0.3.dist-info/RECORD
