Metadata-Version: 2.1
Name: kcore-migrate
Version: 0.0.3
Summary: migration management system for python
Home-page: UNKNOWN
Author: Arun Tigeraniya
Author-email: tigeraniya@gmail.com
License: UNKNOWN
Platform: UNKNOWN
Classifier: Programming Language :: Python :: 3
Classifier: License :: OSI Approved :: MIT License
Classifier: Operating System :: OS Independent
Requires-Python: >=3.6
Requires-Dist: asyncpg
